distributions/Binomialdistribution.py
distributions/Gaussiandistribution.py
distributions/Generaldistribution.py
distributions/__init__.py
essdistributions-1.2.dist-info/METADATA
essdistributions-1.2.dist-info/WHEEL
essdistributions-1.2.dist-info/license.txt
essdistributions-1.2.dist-info/top_level.txt
essdistributions-1.2.dist-info/RECORD
