Metadata-Version: 2.1
Name: essdistributions
Version: 1.2
Summary: Gaussian&Binomial distributions
Home-page: https://github.com/esraahisham753/Gaussian_Binomial_package
Author: Esraa Abduallah
Author-email: esraahisham753@gmail.com
License: UNKNOWN
Platform: UNKNOWN
Classifier: Programming Language :: Python :: 3
Classifier: License :: OSI Approved :: MIT License
Classifier: Operating System :: OS Independent
Requires-Python: >=3.0
